{
    "$schema": [
        {
            "title": "UiPath Agentic Automation Associate",
            "associate": "UiPath",
            "logo": "UiPath",
            "logoSrc": "/portfolio/static/images/UiPath.png",
            "date": "Jan 2026",
            "description": null
        }, {
            "title": "Professional Scrum Developer I (PSD I)",
            "associate": "Scrum.org",
            "logo": "Scrum",
            "logoSrc": "/portfolio/static/images/Scrum.png",
            "date": "Apr 2023",
            "description": null
        }, {
            "title": "Data Analysis with R Programming",
            "associate": "Coursera",
            "logo": "Coursera",
            "logoSrc": "/portfolio/static/images/Coursera.png",
            "date": "Sep 2021",
            "description": null
        }
    ]
}